[{"id":1,"text":"Waste no more time arguing what a good man should be. Be One.","philosopher":"Marcus Aurelius"},{"id":2,"text":"We suffer more in imagination than in reality.","philosopher":"Seneca"},{"id":3,"text":"The best revenge is not to be like your enemy.","philosopher":"Marcus Aurelius"},{"id":4,"text":"I begin to speak only when I'm certain what I'll say isn't better left unsaid.","philosopher":"Cato"},{"id":5,"text":"Seek not for events to happen as you wish but rather wish for events to happen as they do and your life will go smoothly.","philosopher":"Epictetus"},{"id":6,"text":"Do not wait for your ship to come in, swim out to it."}]
